{
  "kind": "command",
  "results": [
    {
      "type": "story",
      "id": 2146,
      "label_ids": [
        5029,
        5032
      ],
      "updated_at": 1419628954000,
      "labels": [
        "eyes-only",
        "new label"
      ]
    },
    {
      "type": "story",
      "id": 2153,
      "label_ids": [
        5029,
        5032
      ],
      "updated_at": 1419628954000,
      "labels": [
        "eyes-only",
        "new label"
      ]
    },
    {
      "type": "story",
      "id": 2177,
      "label_ids": [
        5029,
        5032
      ],
      "updated_at": 1419628954000,
      "labels": [
        "eyes-only",
        "new label"
      ]
    }
  ],
  "activity": {
    "kind": "story_update_activity",
    "guid": "101_286",
    "project_version": 286,
    "message": "Robert Brewster added label \"eyes-only\" to 3 stories",
    "highlight": "added label",
    "changes": [
      {
        "kind": "story",
        "change_type": "update",
        "id": 2146,
        "original_values": {
          "label_ids": [
            5032
          ],
          "updated_at": 1419628923000,
          "labels": [
            "new label"
          ]
        },
        "new_values": {
          "label_ids": [
            5029,
            5032
          ],
          "updated_at": 1419628954000,
          "labels": [
            "eyes-only",
            "new label"
          ]
        },
        "name": "iter3-1",
        "story_type": "chore"
      },
      {
        "kind": "story",
        "change_type": "update",
        "id": 2153,
        "original_values": {
          "label_ids": [
            5032
          ],
          "updated_at": 1419628923000,
          "labels": [
            "new label"
          ]
        },
        "new_values": {
          "label_ids": [
            5029,
            5032
          ],
          "updated_at": 1419628954000,
          "labels": [
            "eyes-only",
            "new label"
          ]
        },
        "name": "iter4-1",
        "story_type": "chore"
      },
      {
        "kind": "story",
        "change_type": "update",
        "id": 2177,
        "original_values": {
          "label_ids": [
            5032
          ],
          "updated_at": 1419628923000,
          "labels": [
            "new label"
          ]
        },
        "new_values": {
          "label_ids": [
            5029,
            5032
          ],
          "updated_at": 1419628954000,
          "labels": [
            "eyes-only",
            "new label"
          ]
        },
        "name": "<script>alert('story content xss')</script>",
        "story_type": "bug"
      }
    ],
    "primary_resources": [
      {
        "kind": "story",
        "id": 2146,
        "name": "iter3-1",
        "story_type": "chore",
        "url": "http://localhost:3000/story/show/2146"
      },
      {
        "kind": "story",
        "id": 2153,
        "name": "iter4-1",
        "story_type": "chore",
        "url": "http://localhost:3000/story/show/2153"
      },
      {
        "kind": "story",
        "id": 2177,
        "name": "<script>alert('story content xss')</script>",
        "story_type": "bug",
        "url": "http://localhost:3000/story/show/2177"
      }
    ],
    "project": {
      "kind": "project",
      "id": 101,
      "name": "Skynet Defense Coordination System"
    },
    "performed_by": {
      "kind": "person",
      "id": 202,
      "name": "Robert Brewster",
      "initials": "rb"
    },
    "occurred_at": 1419628954000
  },
  "mutandum": [
    {
      "type": "story",
      "id": 2177,
      "label_ids": [
        5032
      ],
      "updated_at": 1419628923000,
      "labels": [
        "new label"
      ]
    },
    {
      "type": "story",
      "id": 2153,
      "label_ids": [
        5032
      ],
      "updated_at": 1419628923000,
      "labels": [
        "new label"
      ]
    },
    {
      "type": "story",
      "id": 2146,
      "label_ids": [
        5032
      ],
      "updated_at": 1419628923000,
      "labels": [
        "new label"
      ]
    }
  ],
  "parameters": {
    "label_ids_to_add": [
      5029
    ],
    "label_ids_to_remove": [],
    "ids": [
      2177,
      2153,
      2146
    ]
  },
  "person_id": 202,
  "type": "multi_story_update_label",
  "command_uuid": "7c47c99b-5216-43a5-bdcd-6b7ad4cd2266",
  "project": {
    "id": 101,
    "version": 286
  }
}